vincentpy/__init__.py
vincentpy/add.py
vincentpy-0.0.1.dist-info/LICENSE
vincentpy-0.0.1.dist-info/METADATA
vincentpy-0.0.1.dist-info/WHEEL
vincentpy-0.0.1.dist-info/top_level.txt
vincentpy-0.0.1.dist-info/RECORD
