Metadata-Version: 2.1
Name: vincentpy
Version: 0.0.1
Summary: Test custom package
Author: Vincent Viljoen
Author-email: vv@gmail.com
Classifier: Programming Language :: Python :: 3
Classifier: License :: OSI Approved :: MIT License
Classifier: Operating System :: OS Independent
Requires-Python: >=3.10
License-File: LICENSE
